{
    "bundle": "loc_packages_assets_",
    "scene": "A1S7.RADION",
    "entries": [
        {
            "tag": "A1S7.RADION_TRUCK_0000",
            "en": "Their untiring efforts to sustain and increase the usefulness of those times—",
            "ru_native": "Их усилия по поддержанию и повышению эффективности...",
            "ru_machine": "",
            "ru_final": "",
            "verified": false,
            "uk": "Їхні зусилля щодо підтримки та підвищення ефективності…"
        },
        {
            "tag": "A1S7.RADION_TRUCK_0001",
            "en": "—have not been unobserved; and we now desire to express our very high opinion—",
            "ru_native": "не остались незамеченными. И мы хотим выразить нашу глубокую благодарность...",
            "ru_machine": "",
            "ru_final": "",
            "verified": false,
            "uk": "…не залишилися непоміченими. І ми хочемо висловити нашу глибоку подяку…"
        },
        {
            "tag": "A1S7.RADION_TRUCK_0002",
            "en": "—of the punctual, energetic, and persevering character which, under difficulties—",
            "ru_native": "за своевременность, энергичность и настойчивость, которые, несмотря на...",
            "ru_machine": "",
            "ru_final": "",
            "verified": false,
            "uk": "…за своєчасність, енергійність і наполегливість, які, попри…"
        },
        {
            "tag": "A1S7.RADION_TRUCK_0003",
            "en": "—neither few nor small, we have so admirably preserved.",
            "ru_native": "различные трудности, нам удалось сохранить.",
            "ru_machine": "",
            "ru_final": "",
            "verified": false,
            "uk": "…різні труднощі нам вдалося зберегти."
        },
        {
            "tag": "A1S7.RADION_TRUCK_0004",
            "en": "We therefore beg your acceptance of the accompanying dissolution, which we trust—",
            "ru_native": "Поэтому мы просим вас принять роспуск нашей партии, которая, как мы верим...",
            "ru_machine": "",
            "ru_final": "",
            "verified": false,
            "uk": "Тому ми просимо вас прийняти розпуск нашої компанії, яка, як ми сподіваємося…"
        },
        {
            "tag": "A1S7.RADION_TRUCK_0005",
            "en": "—will continue to be a lamp to your feet, and a guide to your path, as heretofore;",
            "ru_native": "будет и дальше для вас ориентиром, как это было раньше,",
            "ru_machine": "",
            "ru_final": "",
            "verified": false,
            "uk": "…буде й надалі для вас орієнтиром, як це було раніше,"
        },
        {
            "tag": "A1S7.RADION_TRUCK_0006",
            "en": "—and that the same bond which has hitherto united us will continue to hold us—",
            "ru_native": "и останется той самой нитью, которая до сих пор объединяла нас...",
            "ru_machine": "",
            "ru_final": "",
            "verified": false,
            "uk": "…і залишиться тією самою ниткою, яка досі з’єднувала нас…"
        },
        {
            "tag": "A1S7.RADION_TRUCK_0007",
            "en": "—in sisterly communion.",
            "ru_native": "в братский союз.",
            "ru_machine": "",
            "ru_final": "",
            "verified": false,
            "uk": "…у братський союз."
        },
        {
            "tag": "A1S7.RADION_TRUCK_0008",
            "en": "[persistent static]",
            "ru_native": "(радиопомехи)",
            "ru_machine": "",
            "ru_final": "",
            "verified": false,
            "uk": "[радіоперешкоди]"
        }
    ]
}
