{
    "bundle": "loc_packages_assets_",
    "scene": "A2V2.MEDSH2",
    "entries": [
        {
            "tag": "A2V2.MEDSH2_CHOICE_0000",
            "en": "DO NOT DELETE OR CHANGE",
            "ru_native": "DO NOT DELETE OR CHANGE",
            "ru_machine": "",
            "ru_final": "DO NOT DELETE OR CHANGE",
            "verified": true,
            "uk": "DO NOT DELETE OR CHANGE"
        },
        {
            "tag": "A2V2.MEDSH2_CHOICE_0000_OPTION_0000",
            "en": "Adorable.",
            "ru_native": "Миленько.",
            "ru_machine": "",
            "ru_final": "",
            "verified": false,
            "uk": "Чарівно."
        },
        {
            "tag": "A2V2.MEDSH2_CHOICE_0000_OPTION_0001",
            "en": "Refrigerator worthy.",
            "ru_native": "Достойно холодильника.",
            "ru_machine": "",
            "ru_final": "",
            "verified": false,
            "uk": "Я би на холодильник повісила."
        },
        {
            "tag": "A2V2.MEDSH2_JACOB_0000",
            "en": "Uh, the Mountain Spectre is a… hallucination—visual phenomena thing…",
            "ru_native": "Горный призрак... Это вроде галлюцинации, оптическое явление.",
            "ru_machine": "",
            "ru_final": "",
            "verified": false,
            "uk": "Гірський привид… Це галюцинація, оптична ілюзія."
        },
        {
            "tag": "A2V2.MEDSH2_JACOB_0001",
            "en": "It has to do with Parentage.",
            "ru_native": "",
            "ru_machine": "DEEPL Это связано с родительскими отношениями.",
            "ru_final": "",
            "verified": false,
            "uk": ""
        },
        {
            "tag": "A2V2.MEDSH2_JACOB_0002",
            "en": "I thought you wanted to hurry up?",
            "ru_native": "Я думал, ты хотела ускориться?",
            "ru_machine": "",
            "ru_final": "",
            "verified": false,
            "uk": "Я думав, що ти хотіла поквапитись?"
        },
        {
            "tag": "A2V2.MEDSH2_JACOB_0003",
            "en": "Okay, when you said you wanted to look around I didn’t know you meant take the tour…",
            "ru_native": "Когда ты сказала, что хочешь осмотреться, я не рассчитывал на целую экскурсию.",
            "ru_machine": "",
            "ru_final": "",
            "verified": false,
            "uk": "Коли ти сказала, що хочеш тут усе роздивитися, я не розраховував на екскурсію…"
        },
        {
            "tag": "A2V2.MEDSH2_JACOB_0004",
            "en": "At the bottom there’s some… art taped to it. Looks like children’s drawings.",
            "ru_native": "Внизу приклеен какой-то рисунок. Похоже на детские каляки.",
            "ru_machine": "",
            "ru_final": "",
            "verified": false,
            "uk": "Унизу приклеєно якийсь… малюнок. Схоже на дитячі каляки."
        },
        {
            "tag": "A2V2.MEDSH2_JACOB_0005",
            "en": "That’s… weird?",
            "ru_native": "Это... странно?",
            "ru_machine": "",
            "ru_final": "",
            "verified": false,
            "uk": "Як дивно."
        },
        {
            "tag": "A2V2.MEDSH2_JACOB_0006",
            "en": "Is that weird?",
            "ru_native": "Или не странно?",
            "ru_machine": "",
            "ru_final": "",
            "verified": false,
            "uk": "Хіба це не дивно?"
        },
        {
            "tag": "A2V2.MEDSH2_JACOB_0007",
            "en": "Yes… it kind of is… adorable.",
            "ru_native": "Да... Ты права. Мило.",
            "ru_machine": "",
            "ru_final": "",
            "verified": false,
            "uk": "Так, твоя правда. Мило."
        },
        {
            "tag": "A2V2.MEDSH2_JACOB_0008",
            "en": "Yes… it kind of is… charming. In a way.",
            "ru_native": "Да... По-своему очарователен.",
            "ru_machine": "",
            "ru_final": "",
            "verified": false,
            "uk": "Так… По-своєму чарівний."
        },
        {
            "tag": "A2V2.MEDSH2_JACOB_0009",
            "en": "It doesn’t feel weird, if that makes sense…",
            "ru_native": "Он не выглядит странным...",
            "ru_machine": "",
            "ru_final": "",
            "verified": false,
            "uk": "Він не виглядає дивним, якщо в нього є сенс…"
        },
        {
            "tag": "A2V2.MEDSH2_RILEY_0000",
            "en": "The Spectre of the Mountains…",
            "ru_native": "Призрак гор...",
            "ru_machine": "",
            "ru_final": "",
            "verified": false,
            "uk": "Брокенський привид…"
        },
        {
            "tag": "A2V2.MEDSH2_RILEY_0001",
            "en": "Hey, Jacob, you know what this thing is?",
            "ru_native": "Джейкоб, ты знаешь, что это такое?",
            "ru_machine": "",
            "ru_final": "",
            "verified": false,
            "uk": "Гей, Джейкобе, ти знаєш, що це таке?"
        },
        {
            "tag": "A2V2.MEDSH2_RILEY_0002",
            "en": "Looks adorable, to tell you the truth.",
            "ru_native": "По правде говоря, выглядит миленько.",
            "ru_machine": "",
            "ru_final": "",
            "verified": false,
            "uk": "Чесно кажучи, виглядає мило."
        },
        {
            "tag": "A2V2.MEDSH2_RILEY_0003",
            "en": "Looks refrigerator-worthy, to tell you the truth.",
            "ru_native": "Вообще он достоен холодильника.",
            "ru_machine": "",
            "ru_final": "",
            "verified": false,
            "uk": "Взагалі, я би на холодильник повісила."
        }
    ]
}