{
    "bundle": "loc_packages_assets_",
    "scene": "GLOB.RILEY2",
    "entries": [
        {
            "tag": "GLOB.RILEY2_CHOICE_0000",
            "en": "DO NOT DELETE OR CHANGE",
            "ru_native": "DO NOT DELETE OR CHANGE",
            "ru_machine": "",
            "ru_final": "DO NOT DELETE OR CHANGE",
            "verified": true,
            "uk": "DO NOT DELETE OR CHANGE"
        },
        {
            "tag": "GLOB.RILEY2_CHOICE_0000_OPTION_0000",
            "en": "Yup, I’m back.",
            "ru_native": "Я на месте.",
            "ru_machine": "",
            "ru_final": "",
            "verified": false,
            "uk": "Так, я повернулася."
        },
        {
            "tag": "GLOB.RILEY2_CHOICE_0000_OPTION_0001",
            "en": "Thanks for the concern.",
            "ru_native": "Спасибо за заботу.",
            "ru_machine": "",
            "ru_final": "",
            "verified": false,
            "uk": "Дякую за турботу."
        },
        {
            "tag": "GLOB.RILEY2_JACOB_0000",
            "en": "Hey uh—you back? With us? With me—it’s just me.",
            "ru_native": "Эй, ты вернулась? Ты с нами? Точнее со мной.",
            "ru_machine": "",
            "ru_final": "",
            "verified": false,
            "uk": "Гей, ти повернулася? До нас? До мене. Тут лише я."
        },
        {
            "tag": "GLOB.RILEY2_JACOB_0001",
            "en": "You back proper?",
            "ru_native": "Точно вернулась?",
            "ru_machine": "",
            "ru_final": "",
            "verified": false,
            "uk": "Точно повернулася?"
        },
        {
            "tag": "GLOB.RILEY2_JACOB_0002",
            "en": "I—think you are.",
            "ru_native": "Вроде да.",
            "ru_machine": "",
            "ru_final": "",
            "verified": false,
            "uk": "Гадаю, що так."
        },
        {
            "tag": "GLOB.RILEY2_JACOB_0003",
            "en": "So, just checking.",
            "ru_native": "Проверка.",
            "ru_machine": "",
            "ru_final": "",
            "verified": false,
            "uk": "Просто перевіряю."
        },
        {
            "tag": "GLOB.RILEY2_JACOB_0004",
            "en": "Yeah, I gotcha. Good. Great, even.",
            "ru_native": "Блеск. Отлично. Прекрасно даже.",
            "ru_machine": "",
            "ru_final": "",
            "verified": false,
            "uk": "Я з тобою. Чудово. Навіть відмінно."
        },
        {
            "tag": "GLOB.RILEY2_JACOB_0005",
            "en": "Well, yeah, I gotta check! You’d check.",
            "ru_native": "Как иначе! Ты бы тоже беспокоилась.",
            "ru_machine": "",
            "ru_final": "",
            "verified": false,
            "uk": "Так, треба перевірити! Ти б непокоїлася."
        },
        {
            "tag": "GLOB.RILEY2_JACOB_0006",
            "en": "I—think. [quietly, to self] I hope…",
            "ru_native": "Я так думаю. Надеюсь...",
            "ru_machine": "",
            "ru_final": "",
            "verified": false,
            "uk": "Гадаю. [Тихо, до себе] Сподіваюся."
        },
        {
            "tag": "GLOB.RILEY2_JACOB_0007",
            "en": "You seem cogent so, I’m going with yes.",
            "ru_native": "Ладно, молчание – знак согласия.",
            "ru_machine": "",
            "ru_final": "",
            "verified": false,
            "uk": "Здається, переконливо. Отже, це згода."
        },
        {
            "tag": "GLOB.RILEY2_RILEY_0000",
            "en": "Yup, all back. Or—yeah.",
            "ru_native": "Да, я на месте. Или... Да.",
            "ru_machine": "",
            "ru_final": "",
            "verified": false,
            "uk": "Так, точно повернулася. Авжеж."
        },
        {
            "tag": "GLOB.RILEY2_RILEY_0001",
            "en": "Your concern is very sweet, I’m fine.",
            "ru_native": "Спасибо за заботу, я в порядке.",
            "ru_machine": "",
            "ru_final": "",
            "verified": false,
            "uk": "Дякую за турботу, це мило. Я в порядку."
        }
    ]
}